genedisco/__init__.py
genedisco/active_learning_methods/__init__.py
genedisco/active_learning_methods/acquisition_functions/__init__.py
genedisco/active_learning_methods/acquisition_functions/adversarial_bim.py
genedisco/active_learning_methods/acquisition_functions/badge_sampling.py
genedisco/active_learning_methods/acquisition_functions/base_acquisition_function.py
genedisco/active_learning_methods/acquisition_functions/core_set.py
genedisco/active_learning_methods/acquisition_functions/kmeans.py
genedisco/active_learning_methods/acquisition_functions/margin_sampling_acquisition.py
genedisco/active_learning_methods/acquisition_functions/random_acquisition_function.py
genedisco/active_learning_methods/acquisition_functions/uncertainty_acquisition.py
genedisco/active_learning_methods/batchbald_redux/__init__.py
genedisco/active_learning_methods/batchbald_redux/consistent_mc_dropout.py
genedisco/apps/__init__.py
genedisco/apps/active_learning_loop.py
genedisco/apps/plot_results.py
genedisco/apps/run_experiments_application.py
genedisco/apps/single_cycle_application.py
genedisco/datasets/__init__.py
genedisco/datasets/features/__init__.py
genedisco/datasets/features/achilles.py
genedisco/datasets/features/ccle_protein_quantification.py
genedisco/datasets/features/hgnc_names.py
genedisco/datasets/features/string_embedding.py
genedisco/datasets/screens/__init__.py
genedisco/datasets/screens/sanchez_2021_neurons_tau.py
genedisco/datasets/screens/sanchezetal2021_21days.csv
genedisco/datasets/screens/schmidt_2021_t_cells_ifng.py
genedisco/datasets/screens/schmidt_2021_t_cells_il2.py
genedisco/datasets/screens/schmidt_ifng_d1.gene_summary.txt
genedisco/datasets/screens/schmidt_ifng_d2.gene_summary.txt
genedisco/datasets/screens/schmidt_il2_d1.gene_summary.txt
genedisco/datasets/screens/schmidt_il2_d2.gene_summary.txt
genedisco/datasets/screens/zhu_2021_sarscov2_host_factors.csv
genedisco/datasets/screens/zhu_2021_sarscov2_host_factors.py
genedisco-1.0.5.dist-info/LICENSE.txt
genedisco-1.0.5.dist-info/METADATA
genedisco-1.0.5.dist-info/WHEEL
genedisco-1.0.5.dist-info/entry_points.txt
genedisco-1.0.5.dist-info/top_level.txt
genedisco-1.0.5.dist-info/RECORD
