Metadata-Version: 2.1
Name: genedisco
Version: 1.0.5
Home-page: https://gsk.ai/genedisco-challenge/
Author: see README.txt
Author-email: biomedical-ai-external@gsk.com
License: Apache-2.0
Classifier: Programming Language :: Python :: 3
Classifier: License :: OSI Approved :: Apache Software License
Classifier: Operating System :: OS Independent
Requires-Python: >=3.8
License-File: LICENSE.txt
Requires-Dist: six (>=1.11.0)
Requires-Dist: scikit-learn (>=0.22.2)
Requires-Dist: numpy (>=1.14.5)
Requires-Dist: scipy (>=1.5.4)
Requires-Dist: h5py (>=3.0)
Requires-Dist: numba (>=0.49.0)
Requires-Dist: scikit-multilearn (>=0.2.0)
Requires-Dist: dataclasses-json (>=0.5.2)
Requires-Dist: torch (>=1.7.1)
Requires-Dist: toma (>=1.1.0)
Requires-Dist: cmapPy (>=4.0.1)
Requires-Dist: tqdm (>=4.62.1)
Requires-Dist: xxhash (>=2.0.0)
Requires-Dist: requests (>=2.26.0)
Requires-Dist: seaborn (>=0.11.2)
Requires-Dist: slingpy (==0.2.11)
